README.md
setup.py
eason/Cipher.py
eason/__init__.py
eason/printedColor.py
eason.egg-info/PKG-INFO
eason.egg-info/SOURCES.txt
eason.egg-info/dependency_links.txt
eason.egg-info/top_level.txt
eason/JsonProcessor/__init__.py