Metadata-Version: 2.1
Name: eason
Version: 0.1
Summary: A useful python tools package create by EasonC13
Home-page: https://github.com/EasonC13/eason
Author: EasonC13
Author-email: eason.tw.chen@gmail.com
License: MIT
Platform: UNKNOWN
Classifier: Programming Language :: Python :: 3
Classifier: License :: OSI Approved :: MIT License
Classifier: Operating System :: OS Independent
Requires-Python: >=3.2
